polski/__init__.py
polski/main.py
polski-0.0.5.dist-info/DESCRIPTION.rst
polski-0.0.5.dist-info/METADATA
polski-0.0.5.dist-info/RECORD
polski-0.0.5.dist-info/WHEEL
polski-0.0.5.dist-info/entry_points.txt
polski-0.0.5.dist-info/metadata.json
polski-0.0.5.dist-info/top_level.txt
