Metadata-Version: 2.0
Name: polski
Version: 0.0.5
Summary: A command line tool to learn Polish using spaced repetition.
Home-page: http://dirtymonkey.co.uk/polski
Author: Matt Deacalion Stevens
Author-email: matt@dirtymonkey.co.uk
License: MIT
Keywords: polski polish foreign language spaced repetition
Platform: UNKNOWN
Classifier: Development Status :: 3 - Alpha
Classifier: Environment :: Console
Classifier: Intended Audience :: Education
Classifier: License :: OSI Approved :: MIT License
Classifier: Natural Language :: English
Classifier: Operating System :: POSIX :: Linux
Classifier: Operating System :: POSIX :: BSD
Classifier: Programming Language :: Python :: 3.2
Classifier: Programming Language :: Python :: 3.3
Classifier: Programming Language :: Python :: 3.4
Classifier: Topic :: Utilities
Requires-Dist: docopt (>=0.6.2)
Requires-Dist: fuzzywuzzy (>=0.10.0)
Requires-Dist: peewee (>=2.8.1)
